sneks/__init__.py
sneks/config/__init__.py
sneks/config/config.py
sneks/config/definition.py
sneks/core/__init__.py
sneks/core/board.py
sneks/core/cell.py
sneks/core/direction.py
sneks/engine/__init__.py
sneks/engine/mover.py
sneks/engine/registrar.py
sneks/engine/runner.py
sneks/engine/state.py
sneks/gui/__init__.py
sneks/gui/graphics.py
sneks/gui/poster.py
sneks/gui/recorder.py
sneks/interface/__init__.py
sneks/interface/snek.py
sneks/template/__init__.py
sneks/template/submission.py
sneks/validator/__init__.py
sneks/validator/main.py
sneks/validator/test_existance.py
sneks/validator/test_functionality.py
sneks_dev-1.0.1.dist-info/LICENSE
sneks_dev-1.0.1.dist-info/METADATA
sneks_dev-1.0.1.dist-info/WHEEL
sneks_dev-1.0.1.dist-info/entry_points.txt
sneks_dev-1.0.1.dist-info/top_level.txt
sneks_dev-1.0.1.dist-info/RECORD
